tensormaker/__init__.py
tensormaker-0.0.1.dist-info/LICENSE
tensormaker-0.0.1.dist-info/METADATA
tensormaker-0.0.1.dist-info/WHEEL
tensormaker-0.0.1.dist-info/top_level.txt
tensormaker-0.0.1.dist-info/RECORD
